qodabit/__init__.py
qodabit/cli.py
qodabit/ai/__init__.py
qodabit/ai/client.py
qodabit/chat/__init__.py
qodabit/chat/engine.py
qodabit/config/__init__.py
qodabit/config/loader.py
qodabit/reporter/__init__.py
qodabit/reporter/formatter.py
qodabit/scanner/__init__.py
qodabit/scanner/gitleaks.py
qodabit/scanner/orchestrator.py
qodabit/scanner/radon.py
qodabit/scanner/semgrep.py
qodabit/score/__init__.py
qodabit/score/calculator.py
qodabit/score/gates.py
qodabit-0.2.0.dist-info/METADATA
qodabit-0.2.0.dist-info/WHEEL
qodabit-0.2.0.dist-info/entry_points.txt
qodabit-0.2.0.dist-info/RECORD
