Metadata-Version: 2.4
Name: qodabit
Version: 0.2.0
Summary: Security Copilot for AI Devs - Chat-based code auditor
Project-URL: Homepage, https://github.com/qodabit/qodabit
Project-URL: Documentation, https://github.com/qodabit/qodabit#readme
Project-URL: Repository, https://github.com/qodabit/qodabit
Project-URL: Issues, https://github.com/qodabit/qodabit/issues
Author: QodaBit Team
License-Expression: MIT
Keywords: ai,cli,code-review,devtools,sast,security
Classifier: Development Status :: 3 - Alpha
Classifier: Environment :: Console
Classifier: Intended Audience :: Developers
Classifier: License :: OSI Approved :: MIT License
Classifier: Programming Language :: Python :: 3
Classifier: Programming Language :: Python :: 3.9
Classifier: Programming Language :: Python :: 3.10
Classifier: Programming Language :: Python :: 3.11
Classifier: Programming Language :: Python :: 3.12
Classifier: Topic :: Security
Classifier: Topic :: Software Development :: Quality Assurance
Requires-Python: >=3.9
Requires-Dist: anthropic>=0.18.0
Requires-Dist: click>=8.1.0
Requires-Dist: openai>=1.0.0
Requires-Dist: prompt-toolkit>=3.0.0
Requires-Dist: python-dotenv>=1.0.0
Requires-Dist: pyyaml>=6.0
Requires-Dist: rich>=13.0.0
Provides-Extra: dev
Requires-Dist: mypy>=1.0.0; extra == 'dev'
Requires-Dist: pytest-asyncio>=0.21.0; extra == 'dev'
Requires-Dist: pytest-cov>=4.0.0; extra == 'dev'
Requires-Dist: pytest>=7.0.0; extra == 'dev'
Requires-Dist: ruff>=0.1.0; extra == 'dev'
